qubalab/__init__.py
qubalab/display/__init__.py
qubalab/display/plot.py
qubalab/images/__init__.py
qubalab/images/bioio_server.py
qubalab/images/icc_profile_server.py
qubalab/images/image_server.py
qubalab/images/labeled_server.py
qubalab/images/openslide_server.py
qubalab/images/qupath_server.py
qubalab/images/region_2d.py
qubalab/images/utils.py
qubalab/images/wrapped_image_server.py
qubalab/images/metadata/__init__.py
qubalab/images/metadata/image_channel.py
qubalab/images/metadata/image_metadata.py
qubalab/images/metadata/image_shape.py
qubalab/images/metadata/pixel_calibration.py
qubalab/objects/__init__.py
qubalab/objects/classification.py
qubalab/objects/draw.py
qubalab/objects/geojson.py
qubalab/objects/geometry.py
qubalab/objects/image_feature.py
qubalab/objects/object_type.py
qubalab/qupath/__init__.py
qubalab/qupath/qupath_gateway.py
qubalab-0.1.1.dist-info/licenses/LICENSE
qubalab-0.1.1.dist-info/METADATA
qubalab-0.1.1.dist-info/WHEEL
qubalab-0.1.1.dist-info/top_level.txt
qubalab-0.1.1.dist-info/RECORD
