Metadata-Version: 2.4
Name: qubalab
Version: 0.1.1
Summary: A laboratory for exploring quantitative bioimage analysis in Python
Author: Pete Bankhead, Alan O'Callaghan, Léo Leplat
License: Apache-2.0
Project-URL: homepage, https://qupath.github.io/qubalab-docs/
Project-URL: repository, https://github.com/qupath/qubalab
Requires-Python: >=3.11
License-File: LICENSE
Requires-Dist: bioio~=3.0.0
Requires-Dist: bioio-ome-zarr~=2.3.0
Requires-Dist: bioio-ome-tiff~=1.4.0
Requires-Dist: tifffile<=2025.9.9
Requires-Dist: tiffslide~=2.4.0
Requires-Dist: dask-image>=0.6.0
Requires-Dist: py4j~=0.10.9.7
Requires-Dist: geojson~=3.1.0
Requires-Dist: shapely~=2.0.4
Requires-Dist: rasterio~=1.3.10
Requires-Dist: matplotlib~=3.9.0
Requires-Dist: openslide-python~=1.4.0
Requires-Dist: openslide-bin~=4.0.0
Provides-Extra: dev
Requires-Dist: jupyter~=1.0.0; extra == "dev"
Provides-Extra: test
Requires-Dist: pytest~=8.2.2; extra == "test"
Requires-Dist: pytest-html~=4.1.1; extra == "test"
Requires-Dist: coverage~=7.6.5; extra == "test"
Requires-Dist: genbadge[all]~=1.1.1; extra == "test"
Provides-Extra: doc
Requires-Dist: sphinx~=7.4.5; extra == "doc"
Requires-Dist: sphinx-rtd-theme~=2.0.0; extra == "doc"
Dynamic: license-file
